tonie_podcast_sync/__init__.py
tonie_podcast_sync/cli.py
tonie_podcast_sync/config.py
tonie_podcast_sync/podcast.py
tonie_podcast_sync/toniepodcastsync.py
tonie_podcast_sync-3.2.4.dist-info/METADATA
tonie_podcast_sync-3.2.4.dist-info/WHEEL
tonie_podcast_sync-3.2.4.dist-info/entry_points.txt
tonie_podcast_sync-3.2.4.dist-info/licenses/LICENSE
tonie_podcast_sync-3.2.4.dist-info/RECORD
