Metadata-Version: 2.4
Name: tonie-podcast-sync
Version: 3.2.4
Summary: allows synching podcast episodes to creative tonies
Author-email: Alexander Hartmann <16985220+alexhartm@users.noreply.github.com>
License-Expression: MIT
License-File: LICENSE
Keywords: podcast,toniebox
Requires-Python: >=3.10
Requires-Dist: dynaconf>=3.2.3
Requires-Dist: feedparser>=6.0.10
Requires-Dist: pathvalidate>=3.2.0
Requires-Dist: pydub>=0.25.1
Requires-Dist: python-slugify>=8.0.1
Requires-Dist: rich>=13.5.2
Requires-Dist: tomli-w>=1.0.0
Requires-Dist: tonie-api>=0.1.1
Requires-Dist: typer>=0.16.0
Provides-Extra: dev
Requires-Dist: pre-commit>=3.6.0; extra == 'dev'
Requires-Dist: pytest-mock>=3.11.1; extra == 'dev'
Requires-Dist: pytest>=7.4.0; extra == 'dev'
Requires-Dist: responses>=0.23.3; extra == 'dev'
Requires-Dist: ruff>=0.1.13; extra == 'dev'
